LICENSE.md
MANIFEST.in
README.md
requirements.txt
setup.py
aocr/__init__.py
aocr/__main__.py
aocr/defaults.py
aocr.egg-info/PKG-INFO
aocr.egg-info/SOURCES.txt
aocr.egg-info/dependency_links.txt
aocr.egg-info/entry_points.txt
aocr.egg-info/requires.txt
aocr.egg-info/top_level.txt
aocr/model/__init__.py
aocr/model/cnn.py
aocr/model/model.py
aocr/model/seq2seq.py
aocr/model/seq2seq_model.py
aocr/util/__init__.py
aocr/util/bucketdata.py
aocr/util/data_gen.py
aocr/util/dataset.py
aocr/util/export.py