Metadata-Version: 1.1
Name: aocr
Version: 0.6.0
Summary: Optical character recognition model for Tensorflow based on Visual Attention.
Home-page: https://github.com/emedvedev/attention-ocr
Author: Ed Medvedev
Author-email: edward.medvedev@gmail.com
License: MIT
Download-URL: https://github.com/emedvedev/attention-ocr/archive/0.6.0.tar.gz
Platform: UNKNOWN
